sigma/backends/surrealql/__init__.py
sigma/backends/surrealql/surrealql.py
pysigma_backend_surrealql-0.1.0.dist-info/LICENSE
pysigma_backend_surrealql-0.1.0.dist-info/METADATA
pysigma_backend_surrealql-0.1.0.dist-info/WHEEL
pysigma_backend_surrealql-0.1.0.dist-info/RECORD
