Metadata-Version: 2.1
Name: pySigma-backend-surrealql
Version: 0.1.0
Summary: pySigma surrealql backend
Home-page: https://github.com/obviouslynotraffa/pySigma-backend-surrealql
License: LGPL-3.0-only
Author: obviouslynotraffa
Requires-Python: >=3.8,<4.0
Classifier: License :: OSI Approved :: GNU Lesser General Public License v3 (LGPLv3)
Classifier: Programming Language :: Python :: 3
Classifier: Programming Language :: Python :: 3.8
Classifier: Programming Language :: Python :: 3.9
Classifier: Programming Language :: Python :: 3.10
Classifier: Programming Language :: Python :: 3.11
Classifier: Programming Language :: Python :: 3.12
Classifier: Programming Language :: Python :: 3.13
Requires-Dist: pysigma (>=0.11,<0.12)
Project-URL: Repository, https://github.com/obviouslynotraffa/pySigma-backend-surrealql
